airflowctl/__init__.py
airflowctl/__main__.py
airflowctl/exceptions.py
airflowctl/api/__init__.py
airflowctl/api/client.py
airflowctl/api/operations.py
airflowctl/api/datamodels/__init__.py
airflowctl/api/datamodels/auth_generated.py
airflowctl/api/datamodels/generated.py
airflowctl/ctl/__init__.py
airflowctl/ctl/cli_config.py
airflowctl/ctl/cli_parser.py
airflowctl/ctl/console_formatting.py
airflowctl/ctl/commands/__init__.py
airflowctl/ctl/commands/auth_command.py
airflowctl/ctl/commands/config_command.py
airflowctl/ctl/commands/connection_command.py
airflowctl/ctl/commands/dag_command.py
airflowctl/ctl/commands/pool_command.py
airflowctl/ctl/commands/variable_command.py
airflowctl/ctl/commands/version_command.py
airflowctl/ctl/utils/__init__.py
airflowctl/ctl/utils/yaml.py
airflowctl/utils/__init__.py
airflowctl/utils/helpers.py
airflowctl/utils/module_loading.py
apache_airflow_ctl-0.1.0.dist-info/METADATA
apache_airflow_ctl-0.1.0.dist-info/WHEEL
apache_airflow_ctl-0.1.0.dist-info/entry_points.txt
apache_airflow_ctl-0.1.0.dist-info/RECORD
