Metadata-Version: 2.4
Name: apache-airflow-ctl
Version: 0.1.0
Summary: Apache Airflow command line tool for communicating with an Apache Airflow, using the API.
Classifier: Framework :: Apache Airflow
Requires-Python: >=3.10
Requires-Dist: argcomplete>=1.10
Requires-Dist: httpx>=0.27.0
Requires-Dist: keyring>=25.6.0
Requires-Dist: lazy-object-proxy>=1.2.0
Requires-Dist: methodtools>=0.4.7
Requires-Dist: platformdirs>=4.3.6
Requires-Dist: pydantic>=2.11.0
Requires-Dist: rich-argparse>=1.0.0
Requires-Dist: structlog>=25.4.0
Requires-Dist: tabulate>=0.9.0
Requires-Dist: uuid6>=2024.7.10
Provides-Extra: dev
Requires-Dist: keyrings-alt>=5.0.2; extra == 'dev'
